Workbook
Name aporte: PatriSim!$D$16:$D$16
Name dividendo: PatriSim!$D$20:$D$20
Name patromonio: PatriSim!$D$19:$D$19
Name qtd_anos: PatriSim!$D$17:$D$17
Name rendimento_carteira: PatriSim!$D$12:$D$12
Name salario: PatriSim!$D$11:$D$11
Name taxa_rendimento: PatriSim!$D$18:$D$18

Sheet PatriSim
B10: Configurações
B11: Salário | D11: 5000
B12: Rendimento Carteira | D12: 0.01
B13: Sugestão de investimento | D13: =D11*30% -> 1500
B15: Investimento Mensal
B16: Quanto investir por mês? | D16: 500
B17: Por quantos anos? | D17: 5
B18: Taxa de rendimento mensal? | D18: 0.01079
A19: 2 | B19: Patrimônio acumulado? | D19: {=FV(taxa_rendimento,qtd_anos*12,aporte*-1)} -> 41888.457 | G19: 2
A20: 5 | B20: Dividendos mensais? | D20: {=patromonio*rendimento_carteira} -> 418.88457 | G20: 5
A21: 10 | G21: 10
A22: 20 | B22: Cenários | D22: Dividendo | G22: 20
A23: 30 | B23: Quanto em 2 anos? | C23: {=FV(taxa_rendimento,$A19*12,aporte*-1)} -> 13613.814 | D23: {=$C23*rendimento_carteira} -> 136.13814 | G23: 30
B24: Quanto em 5 anos? | C24: {=FV(taxa_rendimento,$A20*12,aporte*-1)} -> 41888.457 | D24: {=$C24*rendimento_carteira} -> 418.88457
B25: Quanto em 10 anos? | C25: {=FV(taxa_rendimento,$A21*12,aporte*-1)} -> 121642.11 | D25: {=$C25*rendimento_carteira} -> 1216.4211
B26: Quanto em 20 anos? | C26: {=FV(taxa_rendimento,$A22*12,aporte*-1)} -> 562599.2 | D26: {=$C26*rendimento_carteira} -> 5625.992
B27: Quanto em 30 anos? | C27: {=FV(taxa_rendimento,$A23*12,aporte*-1)} -> 2161084.8 | D27: {=$C27*rendimento_carteira} -> 21610.848
B29: Perfil | C29: Moderado
B30: Valor a ser investido por mês | C30: 500
B32: Tipo de FII | C32: Percentual sugerido | D32: Valores
B33: Papel | C33: =VLOOKUP($C$29&"-"&B33,Planilha1!B2:E20,4,FALSE) -> 0.32 | D33: =C33*$C$30 -> 160
B34: Tijolo | C34: =VLOOKUP($C$29&"-"&B34,Planilha1!B3:E21,4,FALSE) -> 0.35 | D34: =C34*$C$30 -> 175
B35: Híbridos | C35: =VLOOKUP($C$29&"-"&B35,Planilha1!B4:E22,4,FALSE) -> 0.08 | D35: =C35*$C$30 -> 40
B36: FOFs | C36: =VLOOKUP($C$29&"-"&B36,Planilha1!B5:E23,4,FALSE) -> 0.05 | D36: =C36*$C$30 -> 25
B37: Desenvolvimento | C37: =VLOOKUP($C$29&"-"&B37,Planilha1!B6:E24,4,FALSE) -> 0.1 | D37: =C37*$C$30 -> 50
B38: Hotelarias | C38: =VLOOKUP($C$29&"-"&B38,Planilha1!B7:E25,4,FALSE) -> 0.1 | D38: =C38*$C$30 -> 50
B39: TOTAL | D39: =SUM(D33:D38) -> 500

Sheet Planilha1
B2: Chave | C2: Perfil | D2: Tipo FII | E2: %
B3: =C3&"-"&D3 -> Agressivo-Papel | C3: Agressivo | D3: Papel | E3: 0.3
B4: =C4&"-"&D4 -> Agressivo-Tijolo | C4: Agressivo | D4: Tijolo | E4: 0.5
B5: =C5&"-"&D5 -> Agressivo-Híbridos | C5: Agressivo | D5: Híbridos | E5: 0.1
B6: =C6&"-"&D6 -> Agressivo-FOFs | C6: Agressivo | D6: FOFs | E6: 0.1
B7: =C7&"-"&D7 -> Agressivo-Desenvolvimento | C7: Agressivo | D7: Desenvolvimento | E7: 0
B8: =C8&"-"&D8 -> Agressivo-Hotelarias | C8: Agressivo | D8: Hotelarias | E8: 0
B9: =C9&"-"&D9 -> Moderado-Papel | C9: Moderado | D9: Papel | E9: 0.32
B10: =C10&"-"&D10 -> Moderado-Tijolo | C10: Moderado | D10: Tijolo | E10: 0.35
B11: =C11&"-"&D11 -> Moderado-Híbridos | C11: Moderado | D11: Híbridos | E11: 0.08
B12: =C12&"-"&D12 -> Moderado-FOFs | C12: Moderado | D12: FOFs | E12: 0.05
B13: =C13&"-"&D13 -> Moderado-Desenvolvimento | C13: Moderado | D13: Desenvolvimento | E13: 0.1
B14: =C14&"-"&D14 -> Moderado-Hotelarias | C14: Moderado | D14: Hotelarias | E14: 0.1
... B20: =C20&"-"&D20 -> Conservador-Hotelarias | C20: Conservador | D20: Hotelarias | E20: 0.1
